tictactoejderosia/__init__.py
tictactoejderosia-0.1.0.dist-info/METADATA
tictactoejderosia-0.1.0.dist-info/WHEEL
tictactoejderosia-0.1.0.dist-info/RECORD
