Metadata-Version: 2.1
Name: tictactoejderosia
Version: 0.1.0
Summary: 
Author: jderosia
Author-email: jdero@umich.edu
Requires-Python: >=3.9,<4.0
Classifier: Programming Language :: Python :: 3
Classifier: Programming Language :: Python :: 3.9
Classifier: Programming Language :: Python :: 3.10
Classifier: Programming Language :: Python :: 3.11
Requires-Dist: numpy (>=1.24.3,<2.0.0)
